weatherchecker/__init__.py
weatherchecker/weatherdata.py
weatherchecker-0.0.6.dist-info/LICENSE
weatherchecker-0.0.6.dist-info/METADATA
weatherchecker-0.0.6.dist-info/WHEEL
weatherchecker-0.0.6.dist-info/top_level.txt
weatherchecker-0.0.6.dist-info/RECORD
