Metadata-Version: 2.1
Name: weatherchecker
Version: 0.0.6
Summary: A small weather crawling package
Home-page: https://github.com/roneymathew/weatherchecker
Author: Roney Mathew
Author-email: roneyelirickal@gmail.com
License: UNKNOWN
Platform: UNKNOWN
Classifier: Programming Language :: Python :: 3
Classifier: License :: OSI Approved :: MIT License
Classifier: Operating System :: OS Independent
Requires-Python: >=3.6
Requires-Dist: bs4
Requires-Dist: pandas
